tlx/__init__.py
tlx/apigateway/__init__.py
tlx/dynamodb/__init__.py
tlx/dynamodb/aux.py
tlx/dynamodb/batch.py
tlx/dynamodb/table.py
tlx/dynamodb/cli_apps/__init__.py
tlx/dynamodb/cli_apps/dynamodb_batch_write.py
tlx/util/__init__.py
tlx/util/common.py
tlx/util/helper.py
tlx/util/logger.py
tlx/util/session.py
tlx/util/singleton.py
tlx/util/verification.py
tlx/util/cli_apps/__init__.py
tlx/util/cli_apps/get_aws_creds.py
tlx-0.1.125.data/data/requirements.txt
tlx-0.1.125.data/data/version.txt
tlx-0.1.125.dist-info/LICENSE
tlx-0.1.125.dist-info/METADATA
tlx-0.1.125.dist-info/WHEEL
tlx-0.1.125.dist-info/entry_points.txt
tlx-0.1.125.dist-info/top_level.txt
tlx-0.1.125.dist-info/RECORD
