Metadata-Version: 2.1
Name: tlx
Version: 0.1.125
Summary: Frequently used utilities and code.
Home-page: https://github.com/eL0ck/tlx
Author: eL0ck
Author-email: tpj800@gmail.com
License: Apache
Platform: UNKNOWN
Requires-Python: >=3.6, <4
Requires-Dist: boto3 (>=1.9.199)
Requires-Dist: click (>=6.7)
